geodepoly/__init__.py
geodepoly/batched.py
geodepoly/bench_compare.py
geodepoly/eigs.py
geodepoly/finishers.py
geodepoly/hyper_catalan.py
geodepoly/resummation.py
geodepoly/series_core.py
geodepoly/series_solve.py
geodepoly/solver.py
geodepoly/sympy_plugin.py
geodepoly/util.py
geodepoly/scripts/benchmark.py
geodepoly-0.1.8.dist-info/licenses/LICENSE
geodepoly-0.1.8.dist-info/METADATA
geodepoly-0.1.8.dist-info/WHEEL
geodepoly-0.1.8.dist-info/entry_points.txt
geodepoly-0.1.8.dist-info/top_level.txt
geodepoly-0.1.8.dist-info/RECORD
