Metadata-Version: 2.4
Name: geodepoly
Version: 0.1.8
Summary: Series-reversion polynomial solver with bootstrap and deflation
Author-email: Ric Fulop <ricfulop@mit.edu>
License: MIT
Project-URL: Homepage, https://github.com/ricfulop/geodepoly
Classifier: License :: OSI Approved :: MIT License
Classifier: Programming Language :: Python
Classifier: Programming Language :: Python :: 3
Classifier: Programming Language :: Python :: 3.9
Classifier: Programming Language :: Python :: 3.10
Classifier: Programming Language :: Python :: 3.11
Classifier: Programming Language :: Python :: 3.12
Classifier: Intended Audience :: Science/Research
Classifier: Topic :: Scientific/Engineering :: Mathematics
Requires-Python: >=3.9
License-File: LICENSE
Provides-Extra: dev
Requires-Dist: pytest; extra == "dev"
Requires-Dist: numpy; extra == "dev"
Requires-Dist: pandas; extra == "dev"
Provides-Extra: plots
Requires-Dist: matplotlib; extra == "plots"
Provides-Extra: lint
Requires-Dist: ruff; extra == "lint"
Requires-Dist: black; extra == "lint"
Requires-Dist: mypy; extra == "lint"
Requires-Dist: pytest-cov; extra == "lint"
Requires-Dist: pre-commit; extra == "lint"
Dynamic: license-file
